gabra_converter/__init__.py
gabra_converter/pipeline.py
gabra_converter/converters/__init__.py
gabra_converter/converters/archive_extractor.py
gabra_converter/converters/lexemes/__init__.py
gabra_converter/converters/lexemes/cleaners/__init__.py
gabra_converter/converters/lexemes/cleaners/lemma_capitals_lexeme_cleaner.py
gabra_converter/converters/lexemes/cleaners/lemma_nonmaltese_lexeme_cleaner.py
gabra_converter/converters/lexemes/cleaners/lemma_spaces_lexeme_cleaner.py
gabra_converter/converters/lexemes/cleaners/lexeme_cleaner.py
gabra_converter/converters/lexemes/cleaners/lexeme_cleaner_list.py
gabra_converter/converters/lexemes/cleaners/new_lines_lexeme_cleaner.py
gabra_converter/converters/lexemes/cleaners/pending_lexeme_cleaner.py
gabra_converter/converters/lexemes/exporters/__init__.py
gabra_converter/converters/lexemes/exporters/csv_lexeme_exporter.py
gabra_converter/converters/lexemes/exporters/lexeme_exporter.py
gabra_converter/converters/lexemes/exporters/lexeme_exporter_list.py
gabra_converter/converters/lexemes/pipeline/__init__.py
gabra_converter/converters/lexemes/pipeline/lexeme_pipeline.py
gabra_converter/converters/lexemes/pipeline/listeners/__init__.py
gabra_converter/converters/lexemes/pipeline/listeners/lexeme_pipeline_listener.py
gabra_converter/converters/lexemes/pipeline/listeners/lexeme_pipeline_listener_skip_log.py
gabra_converter/converters/lexemes/row/__init__.py
gabra_converter/converters/lexemes/row/lexeme_row.py
gabra_converter/converters/lexemes/row/lexeme_row_fixer.py
gabra_converter/converters/wordforms/__init__.py
gabra_converter/converters/wordforms/cleaners/__init__.py
gabra_converter/converters/wordforms/cleaners/missing_lexeme_wordform_cleaner.py
gabra_converter/converters/wordforms/cleaners/pending_wordform_cleaner.py
gabra_converter/converters/wordforms/cleaners/surfaceform_capitals_wordform_cleaner.py
gabra_converter/converters/wordforms/cleaners/surfaceform_nonmaltese_wordform_cleaner.py
gabra_converter-1.1.0.dist-info/LICENSE
gabra_converter-1.1.0.dist-info/METADATA
gabra_converter-1.1.0.dist-info/WHEEL
gabra_converter-1.1.0.dist-info/top_level.txt
gabra_converter-1.1.0.dist-info/RECORD
