Metadata-Version: 2.1
Name: gabra-converter
Version: 1.1.0
Summary: A program for converting data from a Ġabra database dump to a more regular and accessible format.
Author-email: Marc Tanti <marc.tanti@um.edu.mt>
License: MIT License
Project-URL: Repository, https://github.com/mtanti/gabra-converter/
Keywords: Ġabra,Gabra,Malti,Maltese
Classifier: Development Status :: 4 - Beta
Classifier: Environment :: Console
Classifier: License :: OSI Approved :: MIT License
Classifier: Natural Language :: English
Classifier: Programming Language :: Python :: 3
Classifier: Typing :: Typed
Classifier: Topic :: Other/Nonlisted Topic
Requires-Python: >=3.9
License-File: LICENSE
Requires-Dist: Sphinx ==5.3.0
Requires-Dist: build ==1.1.1
Requires-Dist: mypy ==0.991
Requires-Dist: pydantic ==1.10.3
Requires-Dist: pyinstaller ==5.6.2
Requires-Dist: pylint ==2.15.9
Requires-Dist: twine ==5.0.0
